{
  "__className__": "serverpod.DatabaseMigration",
  "actions": [
    {
      "__className__": "serverpod.DatabaseMigrationAction",
      "type": "alterTable",
      "alterTable": {
        "__className__": "serverpod.TableMigration",
        "name": "recall_contact",
        "schema": "public",
        "addColumns": [
          {
            "__className__": "serverpod.ColumnDefinition",
            "name": "tags",
            "columnType": 8,
            "isNullable": true,
            "dartType": "List<String>?"
          },
          {
            "__className__": "serverpod.ColumnDefinition",
            "name": "summary",
            "columnType": 0,
            "isNullable": true,
            "dartType": "String?"
          }
        ],
        "deleteColumns": [
          "bio",
          "tier"
        ],
        "modifyColumns": [],
        "addIndexes": [],
        "deleteIndexes": [
          "contact_unique"
        ],
        "addForeignKeys": [],
        "deleteForeignKeys": [],
        "warnings": [
          {
            "__className__": "serverpod.DatabaseMigrationWarning",
            "type": "columnDropped",
            "message": "Column \"bio\" of table \"recall_contact\" will be dropped.",
            "table": "recall_contact",
            "columns": [
              "bio"
            ],
            "destrucive": true
          },
          {
            "__className__": "serverpod.DatabaseMigrationWarning",
            "type": "columnDropped",
            "message": "Column \"tier\" of table \"recall_contact\" will be dropped.",
            "table": "recall_contact",
            "columns": [
              "tier"
            ],
            "destrucive": true
          }
        ]
      }
    },
    {
      "__className__": "serverpod.DatabaseMigrationAction",
      "type": "alterTable",
      "alterTable": {
        "__className__": "serverpod.TableMigration",
        "name": "recall_interaction",
        "schema": "public",
        "addColumns": [],
        "deleteColumns": [],
        "modifyColumns": [],
        "addIndexes": [
          {
            "__className__": "serverpod.IndexDefinition",
            "indexName": "interaction_vec_idx",
            "elements": [
              {
                "__className__": "serverpod.IndexElementDefinition",
                "type": 0,
                "definition": "embedding"
              }
            ],
            "type": "hnsw",
            "isUnique": false,
            "isPrimary": false,
            "vectorDistanceFunction": "l2",
            "vectorColumnType": 10
          }
        ],
        "deleteIndexes": [
          "interaction_vector_idx"
        ],
        "addForeignKeys": [],
        "deleteForeignKeys": [],
        "warnings": []
      }
    },
    {
      "__className__": "serverpod.DatabaseMigrationAction",
      "type": "deleteTable",
      "deleteTable": "recall_user_config"
    },
    {
      "__className__": "serverpod.DatabaseMigrationAction",
      "type": "createTable",
      "createTable": {
        "__className__": "serverpod.TableDefinition",
        "name": "recall_user_config",
        "dartName": "UserConfig",
        "module": "recall",
        "schema": "public",
        "columns": [
          {
            "__className__": "serverpod.ColumnDefinition",
            "name": "id",
            "columnType": 6,
            "isNullable": false,
            "columnDefault": "nextval('recall_user_config_id_seq'::regclass)",
            "dartType": "int?"
          },
          {
            "__className__": "serverpod.ColumnDefinition",
            "name": "userInfoId",
            "columnType": 6,
            "isNullable": false,
            "dartType": "int"
          },
          {
            "__className__": "serverpod.ColumnDefinition",
            "name": "userInfoId",
            "columnType": 6,
            "isNullable": false,
            "dartType": "int"
          },
          {
            "__className__": "serverpod.ColumnDefinition",
            "name": "googleRefreshToken",
            "columnType": 0,
            "isNullable": true,
            "dartType": "String?"
          },
          {
            "__className__": "serverpod.ColumnDefinition",
            "name": "lastGmailHistoryId",
            "columnType": 0,
            "isNullable": true,
            "dartType": "String?"
          },
          {
            "__className__": "serverpod.ColumnDefinition",
            "name": "dailyBriefingTime",
            "columnType": 6,
            "isNullable": false,
            "dartType": "int"
          }
        ],
        "foreignKeys": [
          {
            "__className__": "serverpod.ForeignKeyDefinition",
            "constraintName": "recall_user_config_fk_0",
            "columns": [
              "userInfoId"
            ],
            "referenceTable": "serverpod_user_info",
            "referenceTableSchema": "public",
            "referenceColumns": [
              "id"
            ],
            "onUpdate": 3,
            "onDelete": 3
          }
        ],
        "indexes": [
          {
            "__className__": "serverpod.IndexDefinition",
            "indexName": "recall_user_config_pkey",
            "elements": [
              {
                "__className__": "serverpod.IndexElementDefinition",
                "type": 0,
                "definition": "id"
              }
            ],
            "type": "btree",
            "isUnique": true,
            "isPrimary": true
          },
          {
            "__className__": "serverpod.IndexDefinition",
            "indexName": "user_config_idx",
            "elements": [
              {
                "__className__": "serverpod.IndexElementDefinition",
                "type": 0,
                "definition": "userInfoId"
              }
            ],
            "type": "btree",
            "isUnique": true,
            "isPrimary": false
          }
        ],
        "managed": true
      }
    }
  ],
  "warnings": [
    {
      "__className__": "serverpod.DatabaseMigrationWarning",
      "type": "columnDropped",
      "message": "Column \"bio\" of table \"recall_contact\" will be dropped.",
      "table": "recall_contact",
      "columns": [
        "bio"
      ],
      "destrucive": true
    },
    {
      "__className__": "serverpod.DatabaseMigrationWarning",
      "type": "columnDropped",
      "message": "Column \"tier\" of table \"recall_contact\" will be dropped.",
      "table": "recall_contact",
      "columns": [
        "tier"
      ],
      "destrucive": true
    },
    {
      "__className__": "serverpod.DatabaseMigrationWarning",
      "type": "columnDropped",
      "message": "Column \"lastSyncTime\" of table \"recall_user_config\" will be dropped.",
      "table": "recall_user_config",
      "columns": [
        "lastSyncTime"
      ],
      "destrucive": true
    },
    {
      "__className__": "serverpod.DatabaseMigrationWarning",
      "type": "columnDropped",
      "message": "Column \"gmailHistoryId\" of table \"recall_user_config\" will be dropped.",
      "table": "recall_user_config",
      "columns": [
        "gmailHistoryId"
      ],
      "destrucive": true
    },
    {
      "__className__": "serverpod.DatabaseMigrationWarning",
      "type": "tableDropped",
      "message": "One or more columns are added to table \"recall_user_config\" which cannot be added in a table migration. The complete table will be deleted and recreated.",
      "table": "recall_user_config",
      "columns": [
        "dailyBriefingTime"
      ],
      "destrucive": true
    }
  ],
  "migrationApiVersion": 1
}